exception_dispatcher/__init__.py
exception_dispatcher/dispatchers/__init__.py
exception_dispatcher/dispatchers/django.py
exception_dispatcher/dispatchers/main.py
exception_dispatcher/dispatchers/rest_framework.py
exception_dispatcher/handlers.py
exception_dispatcher/parsers.py
exception_dispatcher/py.typed
exception_dispatcher/types.py
drf_exception_dispatcher-0.1.0.dist-info/LICENSE
drf_exception_dispatcher-0.1.0.dist-info/WHEEL
drf_exception_dispatcher-0.1.0.dist-info/METADATA
drf_exception_dispatcher-0.1.0.dist-info/RECORD
