Metadata-Version: 2.1
Name: drf-exception-dispatcher
Version: 0.1.0
Summary: django-rest-framework exception handler build with functools.singledispatch
Home-page: https://github.com/skarzi/drf-exception-dispatcher
License: MIT
Keywords: django,django-exceptions,django-rest-framework,rest-framework-exceptions,exceptions,exception-handler,exception-dispatcher,exception-parser,singledispatch
Author: Łukasz Skarżyński
Author-email: me@skarzi.com
Requires-Python: >=3.6.1,<4.0.0
Classifier: Development Status :: 4 - Beta
Classifier: Framework :: Django
Classifier: Intended Audience :: Developers
Classifier: License :: OSI Approved :: MIT License
Classifier: Operating System :: OS Independent
Classifier: Programming Language :: Python :: 3
Classifier: Programming Language :: Python :: 3.10
Classifier: Programming Language :: Python :: 3.7
Classifier: Programming Language :: Python :: 3.8
Classifier: Programming Language :: Python :: 3.9
Classifier: Topic :: Internet :: WWW/HTTP
Classifier: Topic :: Software Development :: Libraries :: Python Modules
Project-URL: Repository, https://github.com/skarzi/drf-exception-dispatcher
